sphinx_alice_theme/__init__.py
sphinx_alice_theme/__main__.py
sphinx_alice_theme/breadcrumbs.html
sphinx_alice_theme/footer.html
sphinx_alice_theme/layout.html
sphinx_alice_theme/nav.html
sphinx_alice_theme/search.html
sphinx_alice_theme/searchbox.html
sphinx_alice_theme/theme.conf
sphinx_alice_theme/static/css/normalize.css
sphinx_alice_theme/static/css/sphinx-alice-theme.css
sphinx_alice_theme/static/js/jquery-3.7.1.min.js
sphinx_alice_theme/static/js/gumshoe/gumshoe.polyfills.min.js
sphinx_alice_theme-0.3.0.dist-info/entry_points.txt
sphinx_alice_theme-0.3.0.dist-info/LICENSE
sphinx_alice_theme-0.3.0.dist-info/WHEEL
sphinx_alice_theme-0.3.0.dist-info/METADATA
sphinx_alice_theme-0.3.0.dist-info/RECORD
