Metadata-Version: 2.1
Name: sphinx-alice-theme
Version: 0.3.0
Summary: Provides the Alice theme for Sphinx projects.
Author-email: James Knight <james.d.knight@live.com>
Requires-Python: >=3.9
Classifier: Development Status :: 4 - Beta
Classifier: Environment :: Web Environment
Classifier: Framework :: Sphinx :: Theme
Classifier: Framework :: Sphinx
Classifier: License :: OSI Approved :: BSD License
Classifier: Operating System :: OS Independent
Classifier: Programming Language :: Python :: 3
Classifier: Programming Language :: Python :: 3.9
Classifier: Programming Language :: Python :: 3.10
Classifier: Programming Language :: Python :: 3.11
Classifier: Programming Language :: Python :: 3.12
Classifier: Topic :: Documentation :: Sphinx
Classifier: Topic :: Documentation
Requires-Dist: sphinx>=7.0
Project-URL: Documentation, https://sphinx-alice-theme.jdknight.me/
Project-URL: Download, https://pypi.org/project/sphinx-alice-theme
Project-URL: Source, https://github.com/jdknight/sphinx-alice-theme
